golfshot/__init__.py
golfshot/golf_shot_simulation.py
golfshot-1.0.0.dist-info/LICENSE
golfshot-1.0.0.dist-info/METADATA
golfshot-1.0.0.dist-info/WHEEL
golfshot-1.0.0.dist-info/top_level.txt
golfshot-1.0.0.dist-info/RECORD
